{
  "summary": {
    "overall_coverage": 48.6013986013986,
    "total_statements": 1144,
    "total_covered": 556,
    "modules_at_target": 0,
    "total_modules": 1,
    "tests_passed": 131,
    "tests_failed": 0
  },
  "module_coverage": {
    "utils": {
      "files": [
        {
          "path": "driada.utils.visual",
          "file": "driada/utils/visual.py",
          "statements": 341,
          "covered": 13,
          "coverage_pct": 2.45,
          "tested_by": "utils"
        },
        {
          "path": "driada.utils.neural",
          "file": "driada/utils/neural.py",
          "statements": 21,
          "covered": 3,
          "coverage_pct": 11.11,
          "tested_by": "utils"
        },
        {
          "path": "driada.utils.jit",
          "file": "driada/utils/jit.py",
          "statements": 27,
          "covered": 11,
          "coverage_pct": 38.71,
          "tested_by": "utils"
        },
        {
          "path": "driada.utils.data",
          "file": "driada/utils/data.py",
          "statements": 330,
          "covered": 160,
          "coverage_pct": 43.11,
          "tested_by": "utils"
        },
        {
          "path": "driada.utils.signals",
          "file": "driada/utils/signals.py",
          "statements": 103,
          "covered": 68,
          "coverage_pct": 59.6,
          "tested_by": "utils"
        },
        {
          "path": "driada.utils.naming",
          "file": "driada/utils/naming.py",
          "statements": 13,
          "covered": 10,
          "coverage_pct": 68.42,
          "tested_by": "utils"
        },
        {
          "path": "driada.utils.spatial",
          "file": "driada/utils/spatial.py",
          "statements": 193,
          "covered": 176,
          "coverage_pct": 87.27,
          "tested_by": "utils"
        },
        {
          "path": "driada.utils.plot",
          "file": "driada/utils/plot.py",
          "statements": 39,
          "covered": 38,
          "coverage_pct": 96.61,
          "tested_by": "utils"
        },
        {
          "path": "driada.utils.gif",
          "file": "driada/utils/gif.py",
          "statements": 36,
          "covered": 36,
          "coverage_pct": 100.0,
          "tested_by": "utils"
        },
        {
          "path": "driada.utils.matrix",
          "file": "driada/utils/matrix.py",
          "statements": 24,
          "covered": 24,
          "coverage_pct": 100.0,
          "tested_by": "utils"
        },
        {
          "path": "driada.utils.output",
          "file": "driada/utils/output.py",
          "statements": 17,
          "covered": 17,
          "coverage_pct": 100.0,
          "tested_by": "utils"
        }
      ],
      "file_count": 11,
      "total_statements": 1144,
      "total_covered": 556,
      "simple_average": 64.29818181818182,
      "weighted_average": 45.174291958041955,
      "true_coverage": 48.6013986013986
    }
  },
  "aggregated_file_coverage": {
    "driada.dim_reduction.flexible_ae": 0.0,
    "driada.dim_reduction.losses": 0.0,
    "driada.dimensionality.effective": 0.0,
    "driada.dimensionality.intrinsic": 0.0,
    "driada.dimensionality.linear": 0.0,
    "driada.dimensionality.utils": 0.0,
    "driada.gdrive.auth": 0.0,
    "driada.gdrive.config_template": 0.0,
    "driada.gdrive.upload": 0.0,
    "driada.integration.manifold_analysis": 0.0,
    "driada.network.drawing": 0.0,
    "driada.network.quantum": 0.0,
    "driada.intense.pipelines": 2.14,
    "driada.utils.visual": 2.45,
    "driada.experiment.synthetic.experiment_generators": 2.79,
    "driada.intense.visual": 3.46,
    "driada.intense.disentanglement": 3.6,
    "driada.intense.intense_base": 3.85,
    "driada.network.randomization": 3.98,
    "driada.experiment.synthetic.mixed_selectivity": 4.15,
    "driada.rsa.core": 4.97,
    "driada.dim_reduction.embedding": 5.18,
    "driada.experiment.synthetic.manifold_spatial_3d": 5.29,
    "driada.dim_reduction.manifold_metrics": 5.3,
    "driada.information.ksg": 5.63,
    "driada.experiment.exp_base": 5.79,
    "driada.network.matrix_utils": 5.98,
    "driada.rsa.visual": 5.98,
    "driada.rsa.core_jit": 6.54,
    "driada.dim_reduction.sequences": 6.6,
    "driada.network.net_base": 7.04,
    "driada.network.spectral": 7.46,
    "driada.experiment.synthetic.time_series": 7.53,
    "driada.experiment.exp_build": 7.61,
    "driada.dim_reduction.graph": 7.67,
    "driada.experiment.synthetic.manifold_circular": 7.86,
    "driada.experiment.wavelet_event_detection": 8.01,
    "driada.gdrive.download": 8.02,
    "driada.information.time_series_types": 8.57,
    "driada.intense.stats": 10.18,
    "driada.experiment.spike_reconstruction": 10.31,
    "driada.utils.neural": 11.11,
    "driada.dim_reduction.mvu": 11.24,
    "driada.rsa.integration": 11.76,
    "driada.information.entropy_jit": 12.28,
    "driada.experiment.neuron": 12.96,
    "driada.experiment.wavelet_ridge": 15.0,
    "driada.dim_reduction.dr_base": 15.44,
    "driada.information.entropy": 15.62,
    "driada.network.graph_utils": 16.07,
    "driada.gdrive.gdrive_utils": 16.5,
    "driada.experiment.synthetic.utils": 18.75,
    "driada.dim_reduction.neural": 19.88,
    "driada.dim_reduction.data": 20.3,
    "driada.information.gcmi_jit_utils": 20.97,
    "driada.information.gcmi": 23.76,
    "driada.information.info_base": 29.0,
    "driada.information.info_utils": 31.34,
    "driada.utils.jit": 38.71,
    "driada.experiment.synthetic.core": 42.73,
    "driada.experiment.synthetic.manifold_spatial_2d": 42.86,
    "driada.utils.data": 43.11,
    "driada.utils.signals": 59.6,
    "driada.utils.naming": 68.42,
    "driada.utils.spatial": 87.27,
    "driada.utils.plot": 96.61,
    "driada.utils.gif": 100.0,
    "driada.utils.matrix": 100.0,
    "driada.utils.output": 100.0
  },
  "detailed_results": {
    "utils": {
      "module": "utils",
      "passed": true,
      "test_files": 9,
      "coverage_data": {
        "driada.dim_reduction.flexible_ae": {
          "file_path": "driada/dim_reduction/flexible_ae.py",
          "statements": 126,
          "missed": 126,
          "covered": 0,
          "coverage_pct": 0.0
        },
        "driada.dim_reduction.losses": {
          "file_path": "driada/dim_reduction/losses.py",
          "statements": 232,
          "missed": 232,
          "covered": 0,
          "coverage_pct": 0.0
        },
        "driada.dimensionality.effective": {
          "file_path": "driada/dimensionality/effective.py",
          "statements": 46,
          "missed": 46,
          "covered": 0,
          "coverage_pct": 0.0
        },
        "driada.dimensionality.intrinsic": {
          "file_path": "driada/dimensionality/intrinsic.py",
          "statements": 139,
          "missed": 139,
          "covered": 0,
          "coverage_pct": 0.0
        },
        "driada.dimensionality.linear": {
          "file_path": "driada/dimensionality/linear.py",
          "statements": 58,
          "missed": 58,
          "covered": 0,
          "coverage_pct": 0.0
        },
        "driada.dimensionality.utils": {
          "file_path": "driada/dimensionality/utils.py",
          "statements": 50,
          "missed": 50,
          "covered": 0,
          "coverage_pct": 0.0
        },
        "driada.gdrive.auth": {
          "file_path": "driada/gdrive/auth.py",
          "statements": 22,
          "missed": 22,
          "covered": 0,
          "coverage_pct": 0.0
        },
        "driada.gdrive.config_template": {
          "file_path": "driada/gdrive/config_template.py",
          "statements": 1,
          "missed": 1,
          "covered": 0,
          "coverage_pct": 0.0
        },
        "driada.gdrive.upload": {
          "file_path": "driada/gdrive/upload.py",
          "statements": 37,
          "missed": 37,
          "covered": 0,
          "coverage_pct": 0.0
        },
        "driada.integration.manifold_analysis": {
          "file_path": "driada/integration/manifold_analysis.py",
          "statements": 88,
          "missed": 88,
          "covered": 0,
          "coverage_pct": 0.0
        },
        "driada.network.drawing": {
          "file_path": "driada/network/drawing.py",
          "statements": 143,
          "missed": 143,
          "covered": 0,
          "coverage_pct": 0.0
        },
        "driada.network.quantum": {
          "file_path": "driada/network/quantum.py",
          "statements": 40,
          "missed": 40,
          "covered": 0,
          "coverage_pct": 0.0
        },
        "driada.intense.pipelines": {
          "file_path": "driada/intense/pipelines.py",
          "statements": 294,
          "missed": 284,
          "covered": 10,
          "coverage_pct": 2.14
        },
        "driada.utils.visual": {
          "file_path": "driada/utils/visual.py",
          "statements": 341,
          "missed": 328,
          "covered": 13,
          "coverage_pct": 2.45
        },
        "driada.experiment.synthetic.experiment_generators": {
          "file_path": "driada/experiment/synthetic/experiment_generators.py",
          "statements": 324,
          "missed": 310,
          "covered": 14,
          "coverage_pct": 2.79
        },
        "driada.intense.visual": {
          "file_path": "driada/intense/visual.py",
          "statements": 263,
          "missed": 251,
          "covered": 12,
          "coverage_pct": 3.46
        },
        "driada.intense.disentanglement": {
          "file_path": "driada/intense/disentanglement.py",
          "statements": 150,
          "missed": 142,
          "covered": 8,
          "coverage_pct": 3.6
        },
        "driada.intense.intense_base": {
          "file_path": "driada/intense/intense_base.py",
          "statements": 433,
          "missed": 407,
          "covered": 26,
          "coverage_pct": 3.85
        },
        "driada.network.randomization": {
          "file_path": "driada/network/randomization.py",
          "statements": 321,
          "missed": 304,
          "covered": 17,
          "coverage_pct": 3.98
        },
        "driada.experiment.synthetic.mixed_selectivity": {
          "file_path": "driada/experiment/synthetic/mixed_selectivity.py",
          "statements": 173,
          "missed": 162,
          "covered": 11,
          "coverage_pct": 4.15
        },
        "driada.rsa.core": {
          "file_path": "driada/rsa/core.py",
          "statements": 212,
          "missed": 196,
          "covered": 16,
          "coverage_pct": 4.97
        },
        "driada.dim_reduction.embedding": {
          "file_path": "driada/dim_reduction/embedding.py",
          "statements": 523,
          "missed": 487,
          "covered": 36,
          "coverage_pct": 5.18
        },
        "driada.experiment.synthetic.manifold_spatial_3d": {
          "file_path": "driada/experiment/synthetic/manifold_spatial_3d.py",
          "statements": 140,
          "missed": 129,
          "covered": 11,
          "coverage_pct": 5.29
        },
        "driada.dim_reduction.manifold_metrics": {
          "file_path": "driada/dim_reduction/manifold_metrics.py",
          "statements": 355,
          "missed": 329,
          "covered": 26,
          "coverage_pct": 5.3
        },
        "driada.information.ksg": {
          "file_path": "driada/information/ksg.py",
          "statements": 233,
          "missed": 213,
          "covered": 20,
          "coverage_pct": 5.63
        },
        "driada.experiment.exp_base": {
          "file_path": "driada/experiment/exp_base.py",
          "statements": 557,
          "missed": 506,
          "covered": 51,
          "coverage_pct": 5.79
        },
        "driada.network.matrix_utils": {
          "file_path": "driada/network/matrix_utils.py",
          "statements": 311,
          "missed": 285,
          "covered": 26,
          "coverage_pct": 5.98
        },
        "driada.rsa.visual": {
          "file_path": "driada/rsa/visual.py",
          "statements": 83,
          "missed": 76,
          "covered": 7,
          "coverage_pct": 5.98
        },
        "driada.rsa.core_jit": {
          "file_path": "driada/rsa/core_jit.py",
          "statements": 95,
          "missed": 85,
          "covered": 10,
          "coverage_pct": 6.54
        },
        "driada.dim_reduction.sequences": {
          "file_path": "driada/dim_reduction/sequences.py",
          "statements": 68,
          "missed": 61,
          "covered": 7,
          "coverage_pct": 6.6
        },
        "driada.network.net_base": {
          "file_path": "driada/network/net_base.py",
          "statements": 478,
          "missed": 429,
          "covered": 49,
          "coverage_pct": 7.04
        },
        "driada.network.spectral": {
          "file_path": "driada/network/spectral.py",
          "statements": 49,
          "missed": 44,
          "covered": 5,
          "coverage_pct": 7.46
        },
        "driada.experiment.synthetic.time_series": {
          "file_path": "driada/experiment/synthetic/time_series.py",
          "statements": 104,
          "missed": 93,
          "covered": 11,
          "coverage_pct": 7.53
        },
        "driada.experiment.exp_build": {
          "file_path": "driada/experiment/exp_build.py",
          "statements": 123,
          "missed": 108,
          "covered": 15,
          "coverage_pct": 7.61
        },
        "driada.dim_reduction.graph": {
          "file_path": "driada/dim_reduction/graph.py",
          "statements": 219,
          "missed": 195,
          "covered": 24,
          "coverage_pct": 7.67
        },
        "driada.experiment.synthetic.manifold_circular": {
          "file_path": "driada/experiment/synthetic/manifold_circular.py",
          "statements": 100,
          "missed": 89,
          "covered": 11,
          "coverage_pct": 7.86
        },
        "driada.experiment.wavelet_event_detection": {
          "file_path": "driada/experiment/wavelet_event_detection.py",
          "statements": 243,
          "missed": 217,
          "covered": 26,
          "coverage_pct": 8.01
        },
        "driada.gdrive.download": {
          "file_path": "driada/gdrive/download.py",
          "statements": 129,
          "missed": 114,
          "covered": 15,
          "coverage_pct": 8.02
        },
        "driada.information.time_series_types": {
          "file_path": "driada/information/time_series_types.py",
          "statements": 253,
          "missed": 220,
          "covered": 33,
          "coverage_pct": 8.57
        },
        "driada.intense.stats": {
          "file_path": "driada/intense/stats.py",
          "statements": 117,
          "missed": 100,
          "covered": 17,
          "coverage_pct": 10.18
        },
        "driada.experiment.spike_reconstruction": {
          "file_path": "driada/experiment/spike_reconstruction.py",
          "statements": 73,
          "missed": 63,
          "covered": 10,
          "coverage_pct": 10.31
        },
        "driada.utils.neural": {
          "file_path": "driada/utils/neural.py",
          "statements": 21,
          "missed": 18,
          "covered": 3,
          "coverage_pct": 11.11
        },
        "driada.dim_reduction.mvu": {
          "file_path": "driada/dim_reduction/mvu.py",
          "statements": 67,
          "missed": 57,
          "covered": 10,
          "coverage_pct": 11.24
        },
        "driada.rsa.integration": {
          "file_path": "driada/rsa/integration.py",
          "statements": 46,
          "missed": 38,
          "covered": 8,
          "coverage_pct": 11.76
        },
        "driada.information.entropy_jit": {
          "file_path": "driada/information/entropy_jit.py",
          "statements": 49,
          "missed": 42,
          "covered": 7,
          "coverage_pct": 12.28
        },
        "driada.experiment.neuron": {
          "file_path": "driada/experiment/neuron.py",
          "statements": 244,
          "missed": 202,
          "covered": 42,
          "coverage_pct": 12.96
        },
        "driada.experiment.wavelet_ridge": {
          "file_path": "driada/experiment/wavelet_ridge.py",
          "statements": 128,
          "missed": 107,
          "covered": 21,
          "coverage_pct": 15.0
        },
        "driada.dim_reduction.dr_base": {
          "file_path": "driada/dim_reduction/dr_base.py",
          "statements": 86,
          "missed": 65,
          "covered": 21,
          "coverage_pct": 15.44
        },
        "driada.information.entropy": {
          "file_path": "driada/information/entropy.py",
          "statements": 76,
          "missed": 61,
          "covered": 15,
          "coverage_pct": 15.62
        },
        "driada.network.graph_utils": {
          "file_path": "driada/network/graph_utils.py",
          "statements": 46,
          "missed": 37,
          "covered": 9,
          "coverage_pct": 16.07
        },
        "driada.gdrive.gdrive_utils": {
          "file_path": "driada/gdrive/gdrive_utils.py",
          "statements": 73,
          "missed": 56,
          "covered": 17,
          "coverage_pct": 16.5
        },
        "driada.experiment.synthetic.utils": {
          "file_path": "driada/experiment/synthetic/utils.py",
          "statements": 12,
          "missed": 9,
          "covered": 3,
          "coverage_pct": 18.75
        },
        "driada.dim_reduction.neural": {
          "file_path": "driada/dim_reduction/neural.py",
          "statements": 135,
          "missed": 104,
          "covered": 31,
          "coverage_pct": 19.88
        },
        "driada.dim_reduction.data": {
          "file_path": "driada/dim_reduction/data.py",
          "statements": 125,
          "missed": 92,
          "covered": 33,
          "coverage_pct": 20.3
        },
        "driada.information.gcmi_jit_utils": {
          "file_path": "driada/information/gcmi_jit_utils.py",
          "statements": 234,
          "missed": 182,
          "covered": 52,
          "coverage_pct": 20.97
        },
        "driada.information.gcmi": {
          "file_path": "driada/information/gcmi.py",
          "statements": 272,
          "missed": 198,
          "covered": 74,
          "coverage_pct": 23.76
        },
        "driada.information.info_base": {
          "file_path": "driada/information/info_base.py",
          "statements": 494,
          "missed": 329,
          "covered": 165,
          "coverage_pct": 29.0
        },
        "driada.information.info_utils": {
          "file_path": "driada/information/info_utils.py",
          "statements": 51,
          "missed": 34,
          "covered": 17,
          "coverage_pct": 31.34
        },
        "driada.utils.jit": {
          "file_path": "driada/utils/jit.py",
          "statements": 27,
          "missed": 16,
          "covered": 11,
          "coverage_pct": 38.71
        },
        "driada.experiment.synthetic.core": {
          "file_path": "driada/experiment/synthetic/core.py",
          "statements": 68,
          "missed": 35,
          "covered": 33,
          "coverage_pct": 42.73
        },
        "driada.experiment.synthetic.manifold_spatial_2d": {
          "file_path": "driada/experiment/synthetic/manifold_spatial_2d.py",
          "statements": 132,
          "missed": 70,
          "covered": 62,
          "coverage_pct": 42.86
        },
        "driada.utils.data": {
          "file_path": "driada/utils/data.py",
          "statements": 330,
          "missed": 170,
          "covered": 160,
          "coverage_pct": 43.11
        },
        "driada.utils.signals": {
          "file_path": "driada/utils/signals.py",
          "statements": 103,
          "missed": 35,
          "covered": 68,
          "coverage_pct": 59.6
        },
        "driada.utils.naming": {
          "file_path": "driada/utils/naming.py",
          "statements": 13,
          "missed": 3,
          "covered": 10,
          "coverage_pct": 68.42
        },
        "driada.utils.spatial": {
          "file_path": "driada/utils/spatial.py",
          "statements": 193,
          "missed": 17,
          "covered": 176,
          "coverage_pct": 87.27
        },
        "driada.utils.plot": {
          "file_path": "driada/utils/plot.py",
          "statements": 39,
          "missed": 1,
          "covered": 38,
          "coverage_pct": 96.61
        },
        "driada.utils.gif": {
          "file_path": "driada/utils/gif.py",
          "statements": 36,
          "missed": 0,
          "covered": 36,
          "coverage_pct": 100.0
        },
        "driada.utils.matrix": {
          "file_path": "driada/utils/matrix.py",
          "statements": 24,
          "missed": 0,
          "covered": 24,
          "coverage_pct": 100.0
        },
        "driada.utils.output": {
          "file_path": "driada/utils/output.py",
          "statements": 17,
          "missed": 0,
          "covered": 17,
          "coverage_pct": 100.0
        }
      },
      "test_counts": {
        "passed": 131,
        "failed": 0,
        "skipped": 0,
        "errors": 0
      },
      "returncode": 0,
      "debug_output": "coverage_debug_utils.txt"
    }
  }
}